MANIFEST.in
README.txt
setup.cfg
setup.py
docs/HISTORY.txt
docs/INSTALL.txt
docs/LICENSE.txt
inqbus/__init__.py
inqbus.plone.panorama.egg-info/PKG-INFO
inqbus.plone.panorama.egg-info/SOURCES.txt
inqbus.plone.panorama.egg-info/dependency_links.txt
inqbus.plone.panorama.egg-info/entry_points.txt
inqbus.plone.panorama.egg-info/namespace_packages.txt
inqbus.plone.panorama.egg-info/not-zip-safe
inqbus.plone.panorama.egg-info/requires.txt
inqbus.plone.panorama.egg-info/top_level.txt
inqbus/plone/__init__.py
inqbus/plone/panorama/README.txt
inqbus/plone/panorama/__init__.py
inqbus/plone/panorama/configure.zcml
inqbus/plone/panorama/exportimport.py
inqbus/plone/panorama/tests.py
inqbus/plone/panorama/version.txt
inqbus/plone/panorama/browser/__init__.py
inqbus/plone/panorama/browser/configure.zcml
inqbus/plone/panorama/browser/panoramastarter.pt
inqbus/plone/panorama/browser/panoramastarter.py
inqbus/plone/panorama/browser/javascripts/jquery.panorama.js
inqbus/plone/panorama/browser/stylesheets/jquery.panorama.css
inqbus/plone/panorama/profiles/default/cssregistry.xml
inqbus/plone/panorama/profiles/default/inqbus.plone.panorama.txt
inqbus/plone/panorama/profiles/default/jsregistry.xml
inqbus/plone/panorama/profiles/default/metadata.xml
inqbus/plone/panorama/profiles/default/propertiestool.xml
inqbus/plone/panorama/profiles/default/tinymce.xml
inqbus/plone/panorama/profiles/default/viewlets.xml