Metadata-Version: 1.0
Name: inqbus.plone.panorama
Version: 0.1b
Summary: A Panorama Add-on for Plone, based on jquery and jquery.panorama.
Home-page: http://www.inqbus-hosting.de/open-source-software/inqbus.plone.panorama
Author: Maik Derstappen - Derstappen IT Consulting
Author-email: maik.derstappen@inqbus.de
License: GPL
Platform: UNKNOWN
Classifier: Framework :: Plone
Classifier: Programming Language :: Python
Classifier: Topic :: Software Development :: Libraries :: Python Modules
